shelp/__init__.py
shelp/cli.py
shelp-0.1.0.dist-info/licenses/LICENSE
shelp-0.1.0.dist-info/METADATA
shelp-0.1.0.dist-info/WHEEL
shelp-0.1.0.dist-info/entry_points.txt
shelp-0.1.0.dist-info/top_level.txt
shelp-0.1.0.dist-info/RECORD
