Metadata-Version: 2.4
Name: shelp
Version: 0.1.0
Summary: AI-powered shell-command helper
License: MIT
Requires-Python: >=3.9
License-File: LICENSE
Requires-Dist: openai==1.25
Requires-Dist: httpx<0.27
Requires-Dist: colorama==0.4
Dynamic: license-file
